mini_system_monitor/__init__.py
mini_system_monitor/admin.py
mini_system_monitor/apps.py
mini_system_monitor/models.py
mini_system_monitor/tests.py
mini_system_monitor/views.py
mini_system_monitor/migrations/0001_initial.py
mini_system_monitor/migrations/0002_overview.py
mini_system_monitor/migrations/0003_settings.py
mini_system_monitor/migrations/0004_auto_20210716_2353.py
mini_system_monitor/migrations/__init__.py
mini_system_monitor/static/mini_system_monitor/css/mermaid.css
mini_system_monitor/static/mini_system_monitor/js/gridjs.js
mini_system_monitor/static/mini_system_monitor/js/index.js
mini_system_monitor/templates/admin/env_change_list.html
mini_system_monitor/templates/admin/overview_change_list.html
mini_system_monitor/templates/admin/settings_change_list.html
django_mini_system_monitor-0.3.dist-info/LICENSE
django_mini_system_monitor-0.3.dist-info/METADATA
django_mini_system_monitor-0.3.dist-info/WHEEL
django_mini_system_monitor-0.3.dist-info/top_level.txt
django_mini_system_monitor-0.3.dist-info/RECORD
